tinyjam/__init__.py
tinyjam/__main__.py
tinyjam/cli.py
tinyjam-1.0.0.dist-info/licenses/LICENSE
tinyjam-1.0.0.dist-info/METADATA
tinyjam-1.0.0.dist-info/WHEEL
tinyjam-1.0.0.dist-info/entry_points.txt
tinyjam-1.0.0.dist-info/top_level.txt
tinyjam-1.0.0.dist-info/RECORD
