Metadata-Version: 2.4
Name: tinyjam
Version: 1.0.0
Summary: Jam to NPR Tiny Desk concerts with downloads and streaming
Author: Arya Kaul
License:                            ETHICAL LICENSE 
Project-URL: Homepage, https://github.com/aryakaul/tinyjam
Project-URL: Repository, https://github.com/aryakaul/tinyjam
Keywords: npr,tiny desk,music,yt-dlp,mpv
Classifier: Development Status :: 5 - Production/Stable
Classifier: Environment :: Console
Classifier: Intended Audience :: End Users/Desktop
Classifier: Programming Language :: Python :: 3
Classifier: Programming Language :: Python :: 3.10
Classifier: Programming Language :: Python :: 3.11
Classifier: Programming Language :: Python :: 3.12
Classifier: Topic :: Multimedia :: Sound/Audio :: Players
Requires-Python: >=3.9
License-File: LICENSE
Requires-Dist: loguru>=0.7
Requires-Dist: tqdm>=4.66
Requires-Dist: yt-dlp>=2025
Dynamic: license-file
